note/__init__.py
note/note.py
note/messenger/__init__.py
note/messenger/messenger.py
note/messenger/email/__init__.py
note/messenger/email/mail.py
note/messenger/line/__init__.py
note/messenger/line/line.py
note/messenger/telegram/__init__.py
note/messenger/telegram/telegram.py
py_multi_pager-0.2.2.dist-info/AUTHORS.md
py_multi_pager-0.2.2.dist-info/METADATA
py_multi_pager-0.2.2.dist-info/WHEEL
py_multi_pager-0.2.2.dist-info/top_level.txt
py_multi_pager-0.2.2.dist-info/RECORD
