Metadata-Version: 2.1
Name: py-multi-pager
Version: 0.2.2
Summary: Easy and fast python SNS notifier.
Home-page: https://github.com/archdo0909/NotiPy
Author: Doyeon Kim
Author-email: archdo0909@gmail.com
License: MIT
Platform: UNKNOWN
Classifier: Programming Language :: Python :: 3
Classifier: License :: OSI Approved :: MIT License
